Workbook

Sheet MASTER
C2: ÉVALUATION DES COMPÉTENCES EN PRATIQUE | Q2: ETML
D3: INFORMATICIEN-NE | H3: Nom et Prénom : | N3: Nom du projet :
H4: Année de formation - classe : | N4: Périodes :
H5: Enseignant : | N5: Dates :
F8: LARGEMENT ACQUIS | I8: ACQUIS | L8: PARTIELLEMENT ACQUIS | O8: NON ACQUIS | R8: Résultat
C9: COMPÉTENCES | D9: PROFESSIONNELLES | E9: Rythme de travail Rapidité, Efficacité | F9: o o o | G9: Rapide et soutenu Optimale | I9: o o o | J9: Productivité normale Respect des délais fixés | L9: o o o | M9: Lent ou irrégulier Hors délais | O9: o o o | P9: Trop lent Pas concerné par les délais
E10: Qualité du travail | F10: o o o | G10: Travail utilisable et transmissible | I10: o o o | J10: Travail utilisable et transmissible avec retouches | L10: o o o | M10: Travail nécessitant des améliorations pour être utilisable | O10: o o o | P10: Travail inutilisable
E11: Niveau de maîtrise technique | F11: o o o | G11: Maîtrise | I11: o o o | J11: Comprend et applique | L11: o o o | M11: A des lacunes, applique par mimétisme | O11: o o o | P11: Echec dans les notions de base
E12: Autonomie | F12: o o o | G12: Indépendant | I12: o o o | J12: Aide justifiée | L12: o o o | M12: Souvent besoin d'aide | O12: o o o | P12: Dépendant
D13: METHODOLOGIQUES | E13: Processus de travail | F13: o o o | G13: Intègration des règles et processus de travail | I13: o o o | J13: Respect des règles de processus de travail | L13: o o o | M13: Peu concerné | O13: o o o | P13: Pas concerné
E14: Expression orale et écrite Technique de présentation | F14: o o o | G14: Maîtrise les différents moyens et outils de communication et de documentation | I14: o o o | J14: Utilise les différents moyens et outils de communication et de documentation | L14: o o o | M14: N'utilise pas toujours les différents moyens et outils de communication et de documentation | O14: o o o | P14: Ignore la plupart des moyens et outils de communication et de documentation
E15: Approche de la durabilité et de l’innovation | F15: o o o | G15: Recours systématique aux technologies et moyens qui ménagent les ressources et les coûts | I15: o o o | J15: Utilisation régulière des technologies et moyens qui ménagent les ressources | L15: o o o | M15: Peu concerné | O15: o o o | P15: Pas concerné
D16: SOCIALES | E16: Aptitude au travail en équipe Gestion des conflits Communication | F16: o o o | G16: Influence positivement le groupe Réagit de manière réfléchie et cherche des solutions | I16: o o o | J16: Maintien les bonnes relations Ne provoque pas de conflit et participe aux solutions | L16: o o o | M16: Ne participe pas à la cohésion du groupe Réagit de manière irréfléchie et/ou disproportionnée | O16: o o o | P16: Influence négative marquée
C18: Remarque(s) : | N18: Date | P18: Signature | Q18: Totaux
L20: Enseignant :
L22: Apprenti :
P24: Résultat final | Q24: =IF(COUNTIF(R9:S15,"NA")>0, "NA",IF(COUNTIF(R9:S15,"PA")>0,"PA", IF(COUNTIF(R9:S15,"A")>=4,"A","LA"))) -> LA

Sheet Contextualisation
C2: ÉVALUATION DES COMPÉTENCES EN PRATIQUE | Q2: ETML
D3: INFORMATICIEN-NE | H3: Nom et Prénom : | N3: Nom du projet :
H4: Année de formation - classe : | N4: Périodes :
H5: Enseignant : | N5: Dates :
F8: LARGEMENT ACQUIS | I8: ACQUIS | L8: PARTIELLEMENT ACQUIS | O8: NON ACQUIS | R8: Résultat
C9: COMPÉTENCES | D9: PROFESSIONNELLES | E9: Nombre de traces d'activité par session | F9: 10 ou plus en moyenne | I9: 5 ou plus chaque semaine | L9: Moins de 5 pour plus d'une semaine | O9: 1-2 ou moins
E10: Revue de code sur une pull request | F10: Menée par le développeur de manière structurée, complète et convaincante, au premier essai | I10: Quelques hésitations, explications pas claires, mais ensemble cohérent et complet, pull request mergée. Ou plusieurs tentatives | L10: La démarche demandée n'est pas complètement appliquée, ou Les explications ne sont pas convaicantes. La pull request n'est pas mergée | O10: La revue n'a pas eu lieu
E11: US Test | F11: Résultat mergeable tel quel | I11: Résultat mergeable moyennant quelques retouches | L11: Résultat nécessitant des retouches majeures | O11: Résultat à oublier et à recommencer.
E12: Sollicitations injustifiées Blocages prolongés Recours à l'IA Concentration | F12: 3 jokers restants | I12: Au moins un joker restant | L12: plus de joker
D13: METHODOLOGIQUES | E13: Journal de travail + Github Project | F13: Journal complet, des détails sont fournis pour toutes les tâches > 45min Présentation impeccable Les US sont suivies avec précision dans GHProject | I13: Journal complet Suivi dans GHProject OK, mais pas forcément toujours à jour | L13: Plusieurs "trous" et/ou Tâche de plus de 2h sans détails Une US manquante dans GHProject | O13: Pire
E14: Readme du repo Rapport IA | F14: Complet, clair, rien à redire | I14: Quelques imprécisions dans les informatios Rapport trop court, mais >90% | L14: Manque d'informations dans le readme Rapport généré par IA | O14: Pire
E15: Pas évalué
C18: Remarque(s) : | N18: Date | P18: Signature | Q18: Totaux
L20: Enseignant :
L22: Apprenti :
P24: Résultat final | Q24: =IF(COUNTIF(R9:S15,"NA")>0, "NA",IF(COUNTIF(R9:S15,"PA")>0,"PA", IF(COUNTIF(R9:S15,"A")>=4,"A","LA"))) -> LA

Sheet Consolidation
A2: Année de formation - classe : | B2: 2025-2026 / CMID2A
A3: Enseignant : | B3: Xavier Carrel | C3: #VALUE!
A4: Nom du projet : | B4: P_BULLE
A5: Périodes : | B5: 40
A6: Dates : | B6: Du 14.1.2026 au 13.3.2026
A8: Apprentis : | B8: Aaron | C8: Résultats : | D8: =INDIRECT(B8&"!Q24")
B9: Camille | D9: =INDIRECT(B9&"!Q24")
B10: Carl | D10: =INDIRECT(B10&"!Q24")
B11: David | D11: =INDIRECT(B11&"!Q24")
B12: Elias | D12: =INDIRECT(B12&"!Q24")
B13: Jonathan | D13: =INDIRECT(B13&"!Q24")
B14: Kilian | D14: =INDIRECT(B14&"!Q24")
B15: Latif | D15: =INDIRECT(B15&"!Q24")
B16: Néo | D16: =INDIRECT(B16&"!Q24")
B17: Ryan | D17: =INDIRECT(B17&"!Q24")
B18: Stepan | D18: =INDIRECT(B18&"!Q24")
B19: ThomasP | D19: =INDIRECT(B19&"!Q24")
B20: ThomasR | D20: =INDIRECT(B20&"!Q24")

Sheet Aaron
C2: ÉVALUATION DES COMPÉTENCES EN PRATIQUE | Q2: ETML
D3: INFORMATICIEN-NE | H3: Nom et Prénom : | I3: =Consolidation!B20 -> ThomasR | N3: Nom du projet : | O3: =Consolidation!B4 -> P_BULLE
H4: Année de formation - classe : | I4: =Consolidation!B2 -> 2025-2026 / CMID2A | N4: Périodes : | O4: =Consolidation!B5 -> 40
H5: Enseignant : | I5: =Consolidation!B3 -> Xavier Carrel | N5: Dates : | O5: =Consolidation!B6 -> Du 14.1.2026 au 13.3.2026
F8: LARGEMENT ACQUIS | I8: ACQUIS | L8: PARTIELLEMENT ACQUIS | O8: NON ACQUIS | R8: Résultat
C9: COMPÉTENCES | D9: PROFESSIONNELLES | E9: Rythme de travail Rapidité, Efficacité | F9: o o o | G9: Rapide et soutenu Optimale | I9: o o o | J9: Productivité normale Respect des délais fixés | L9: o o o | M9: Lent ou irrégulier Hors délais | O9: o o o | P9: Trop lent Pas concerné par les délais
E10: Qualité du travail | F10: o o o | G10: Travail utilisable et transmissible | I10: o o o | J10: Travail utilisable et transmissible avec retouches | L10: o o o | M10: Travail nécessitant des améliorations pour être utilisable | O10: o o o | P10: Travail inutilisable
E11: Niveau de maîtrise technique | F11: o o o | G11: Maîtrise | I11: o o o | J11: Comprend et applique | L11: o o o | M11: A des lacunes, applique par mimétisme | O11: o o o | P11: Echec dans les notions de base
E12: Autonomie | F12: o o o | G12: Indépendant | I12: o o o | J12: Aide justifiée | L12: o o o | M12: Souvent besoin d'aide | O12: o o o | P12: Dépendant
D13: METHODOLOGIQUES | E13: Processus de travail | F13: o o o | G13: Intègration des règles et processus de travail | I13: o o o | J13: Respect des règles de processus de travail | L13: o o o | M13: Peu concerné | O13: o o o | P13: Pas concerné
E14: Expression orale et écrite Technique de présentation | F14: o o o | G14: Maîtrise les différents moyens et outils de communication et de documentation | I14: o o o | J14: Utilise les différents moyens et outils de communication et de documentation | L14: o o o | M14: N'utilise pas toujours les différents moyens et outils de communication et de documentation | O14: o o o | P14: Ignore la plupart des moyens et outils de communication et de documentation
E15: Approche de la durabilité et de l’innovation | F15: o o o | G15: Recours systématique aux technologies et moyens qui ménagent les ressources et les coûts | I15: o o o | J15: Utilisation régulière des technologies et moyens qui ménagent les ressources | L15: o o o | M15: Peu concerné | O15: o o o | P15: Pas concerné
D16: SOCIALES | E16: Aptitude au travail en équipe Gestion des conflits Communication | F16: o o o | G16: Influence positivement le groupe Réagit de manière réfléchie et cherche des solutions | I16: o o o | J16: Maintien les bonnes relations Ne provoque pas de conflit et participe aux solutions | L16: o o o | M16: Ne participe pas à la cohésion du groupe Réagit de manière irréfléchie et/ou disproportionnée | O16: o o o | P16: Influence négative marquée
C18: Remarque(s) : | N18: Date | P18: Signature | Q18: Totaux
L20: Enseignant : | N20: (tbd) | P20: =Consolidation!C3 -> #VALUE!
L22: Apprenti :
P24: Résultat final | Q24: =IF(COUNTBLANK(R9:S15)=14,"",IF(COUNTIF(R9:S15,"NA")>0,"NA",IF(COUNTIF(R9:S15,"PA")>0,"PA","A")))

Sheet Camille
C2: ÉVALUATION DES COMPÉTENCES EN PRATIQUE | Q2: ETML
D3: INFORMATICIEN-NE | H3: Nom et Prénom : | I3: =Consolidation!B16 -> Néo | N3: Nom du projet : | O3: =Consolidation!B4 -> P_BULLE
H4: Année de formation - classe : | I4: =Consolidation!B2 -> 2025-2026 / CMID2A | N4: Périodes : | O4: =Consolidation!B5 -> 40
H5: Enseignant : | I5: =Consolidation!B3 -> Xavier Carrel | N5: Dates : | O5: =Consolidation!B6 -> Du 14.1.2026 au 13.3.2026
F8: LARGEMENT ACQUIS | I8: ACQUIS | L8: PARTIELLEMENT ACQUIS | O8: NON ACQUIS | R8: Résultat
C9: COMPÉTENCES | D9: PROFESSIONNELLES | E9: Rythme de travail Rapidité, Efficacité | F9: o o o | G9: Rapide et soutenu Optimale | I9: o o o | J9: Productivité normale Respect des délais fixés | L9: o o o | M9: Lent ou irrégulier Hors délais | O9: o o o | P9: Trop lent Pas concerné par les délais
E10: Qualité du travail | F10: o o o | G10: Travail utilisable et transmissible | I10: o o o | J10: Travail utilisable et transmissible avec retouches | L10: o o o | M10: Travail nécessitant des améliorations pour être utilisable | O10: o o o | P10: Travail inutilisable
E11: Niveau de maîtrise technique | F11: o o o | G11: Maîtrise | I11: o o o | J11: Comprend et applique | L11: o o o | M11: A des lacunes, applique par mimétisme | O11: o o o | P11: Echec dans les notions de base
E12: Autonomie | F12: o o o | G12: Indépendant | I12: o o o | J12: Aide justifiée | L12: o o o | M12: Souvent besoin d'aide | O12: o o o | P12: Dépendant
D13: METHODOLOGIQUES | E13: Processus de travail | F13: o o o | G13: Intègration des règles et processus de travail | I13: o o o | J13: Respect des règles de processus de travail | L13: o o o | M13: Peu concerné | O13: o o o | P13: Pas concerné
E14: Expression orale et écrite Technique de présentation | F14: o o o | G14: Maîtrise les différents moyens et outils de communication et de documentation | I14: o o o | J14: Utilise les différents moyens et outils de communication et de documentation | L14: o o o | M14: N'utilise pas toujours les différents moyens et outils de communication et de documentation | O14: o o o | P14: Ignore la plupart des moyens et outils de communication et de documentation
E15: Approche de la durabilité et de l’innovation | F15: o o o | G15: Recours systématique aux technologies et moyens qui ménagent les ressources et les coûts | I15: o o o | J15: Utilisation régulière des technologies et moyens qui ménagent les ressources | L15: o o o | M15: Peu concerné | O15: o o o | P15: Pas concerné
D16: SOCIALES | E16: Aptitude au travail en équipe Gestion des conflits Communication | F16: o o o | G16: Influence positivement le groupe Réagit de manière réfléchie et cherche des solutions | I16: o o o | J16: Maintien les bonnes relations Ne provoque pas de conflit et participe aux solutions | L16: o o o | M16: Ne participe pas à la cohésion du groupe Réagit de manière irréfléchie et/ou disproportionnée | O16: o o o | P16: Influence négative marquée
C18: Remarque(s) : | N18: Date | P18: Signature | Q18: Totaux
L20: Enseignant : | N20: (tbd) | P20: =Consolidation!C3 -> #VALUE!
L22: Apprenti :
P24: Résultat final | Q24: =IF(COUNTBLANK(R9:S15)=14,"",IF(COUNTIF(R9:S15,"NA")>0,"NA",IF(COUNTIF(R9:S15,"PA")>0,"PA","A")))

Sheet Carl
C2: ÉVALUATION DES COMPÉTENCES EN PRATIQUE | Q2: ETML
D3: INFORMATICIEN-NE | H3: Nom et Prénom : | I3: =Consolidation!B8 -> Aaron | N3: Nom du projet : | O3: =Consolidation!B4 -> P_BULLE
H4: Année de formation - classe : | I4: =Consolidation!B2 -> 2025-2026 / CMID2A | N4: Périodes : | O4: =Consolidation!B5 -> 40
H5: Enseignant : | I5: =Consolidation!B3 -> Xavier Carrel | N5: Dates : | O5: =Consolidation!B6 -> Du 14.1.2026 au 13.3.2026
F8: LARGEMENT ACQUIS | I8: ACQUIS | L8: PARTIELLEMENT ACQUIS | O8: NON ACQUIS | R8: Résultat
C9: COMPÉTENCES | D9: PROFESSIONNELLES | E9: Rythme de travail Rapidité, Efficacité | F9: o o o | G9: Rapide et soutenu Optimale | I9: o o o | J9: Productivité normale Respect des délais fixés | L9: o o o | M9: Lent ou irrégulier Hors délais | O9: o o o | P9: Trop lent Pas concerné par les délais
E10: Qualité du travail | F10: o o o | G10: Travail utilisable et transmissible | I10: o o o | J10: Travail utilisable et transmissible avec retouches | L10: o o o | M10: Travail nécessitant des améliorations pour être utilisable | O10: o o o | P10: Travail inutilisable
E11: Niveau de maîtrise technique | F11: o o o | G11: Maîtrise | I11: o o o | J11: Comprend et applique | L11: o o o | M11: A des lacunes, applique par mimétisme | O11: o o o | P11: Echec dans les notions de base
E12: Autonomie | F12: o o o | G12: Indépendant | I12: o o o | J12: Aide justifiée | L12: o o o | M12: Souvent besoin d'aide | O12: o o o | P12: Dépendant
D13: METHODOLOGIQUES | E13: Processus de travail | F13: o o o | G13: Intègration des règles et processus de travail | I13: o o o | J13: Respect des règles de processus de travail | L13: o o o | M13: Peu concerné | O13: o o o | P13: Pas concerné
E14: Expression orale et écrite Technique de présentation | F14: o o o | G14: Maîtrise les différents moyens et outils de communication et de documentation | I14: o o o | J14: Utilise les différents moyens et outils de communication et de documentation | L14: o o o | M14: N'utilise pas toujours les différents moyens et outils de communication et de documentation | O14: o o o | P14: Ignore la plupart des moyens et outils de communication et de documentation
E15: Approche de la durabilité et de l’innovation | F15: o o o | G15: Recours systématique aux technologies et moyens qui ménagent les ressources et les coûts | I15: o o o | J15: Utilisation régulière des technologies et moyens qui ménagent les ressources | L15: o o o | M15: Peu concerné | O15: o o o | P15: Pas concerné
D16: SOCIALES | E16: Aptitude au travail en équipe Gestion des conflits Communication | F16: o o o | G16: Influence positivement le groupe Réagit de manière réfléchie et cherche des solutions | I16: o o o | J16: Maintien les bonnes relations Ne provoque pas de conflit et participe aux solutions | L16: o o o | M16: Ne participe pas à la cohésion du groupe Réagit de manière irréfléchie et/ou disproportionnée | O16: o o o | P16: Influence négative marquée
C18: Remarque(s) : | N18: Date | P18: Signature | Q18: Totaux
L20: Enseignant : | N20: (tbd) | P20: =Consolidation!C3 -> #VALUE!
L22: Apprenti :
P24: Résultat final | Q24: =IF(COUNTBLANK(R9:S15)=14,"",IF(COUNTIF(R9:S15,"NA")>0,"NA",IF(COUNTIF(R9:S15,"PA")>0,"PA","A")))

Sheet David
C2: ÉVALUATION DES COMPÉTENCES EN PRATIQUE | Q2: ETML
D3: INFORMATICIEN-NE | H3: Nom et Prénom : | I3: =Consolidation!B18 -> Stepan | N3: Nom du projet : | O3: =Consolidation!B4 -> P_BULLE
H4: Année de formation - classe : | I4: =Consolidation!B2 -> 2025-2026 / CMID2A | N4: Périodes : | O4: =Consolidation!B5 -> 40
H5: Enseignant : | I5: =Consolidation!B3 -> Xavier Carrel | N5: Dates : | O5: =Consolidation!B6 -> Du 14.1.2026 au 13.3.2026
F8: LARGEMENT ACQUIS | I8: ACQUIS | L8: PARTIELLEMENT ACQUIS | O8: NON ACQUIS | R8: Résultat
C9: COMPÉTENCES | D9: PROFESSIONNELLES | E9: Rythme de travail Rapidité, Efficacité | F9: o o o | G9: Rapide et soutenu Optimale | I9: o o o | J9: Productivité normale Respect des délais fixés | L9: o o o | M9: Lent ou irrégulier Hors délais | O9: o o o | P9: Trop lent Pas concerné par les délais
E10: Qualité du travail | F10: o o o | G10: Travail utilisable et transmissible | I10: o o o | J10: Travail utilisable et transmissible avec retouches | L10: o o o | M10: Travail nécessitant des améliorations pour être utilisable | O10: o o o | P10: Travail inutilisable
E11: Niveau de maîtrise technique | F11: o o o | G11: Maîtrise | I11: o o o | J11: Comprend et applique | L11: o o o | M11: A des lacunes, applique par mimétisme | O11: o o o | P11: Echec dans les notions de base
E12: Autonomie | F12: o o o | G12: Indépendant | I12: o o o | J12: Aide justifiée | L12: o o o | M12: Souvent besoin d'aide | O12: o o o | P12: Dépendant
D13: METHODOLOGIQUES | E13: Processus de travail | F13: o o o | G13: Intègration des règles et processus de travail | I13: o o o | J13: Respect des règles de processus de travail | L13: o o o | M13: Peu concerné | O13: o o o | P13: Pas concerné
E14: Expression orale et écrite Technique de présentation | F14: o o o | G14: Maîtrise les différents moyens et outils de communication et de documentation | I14: o o o | J14: Utilise les différents moyens et outils de communication et de documentation | L14: o o o | M14: N'utilise pas toujours les différents moyens et outils de communication et de documentation | O14: o o o | P14: Ignore la plupart des moyens et outils de communication et de documentation
E15: Approche de la durabilité et de l’innovation | F15: o o o | G15: Recours systématique aux technologies et moyens qui ménagent les ressources et les coûts | I15: o o o | J15: Utilisation régulière des technologies et moyens qui ménagent les ressources | L15: o o o | M15: Peu concerné | O15: o o o | P15: Pas concerné
D16: SOCIALES | E16: Aptitude au travail en équipe Gestion des conflits Communication | F16: o o o | G16: Influence positivement le groupe Réagit de manière réfléchie et cherche des solutions | I16: o o o | J16: Maintien les bonnes relations Ne provoque pas de conflit et participe aux solutions | L16: o o o | M16: Ne participe pas à la cohésion du groupe Réagit de manière irréfléchie et/ou disproportionnée | O16: o o o | P16: Influence négative marquée
C18: Remarque(s) : | N18: Date | P18: Signature | Q18: Totaux
L20: Enseignant : | N20: (tbd) | P20: =Consolidation!C3 -> #VALUE!
L22: Apprenti :
P24: Résultat final | Q24: =IF(COUNTBLANK(R9:S15)=14,"",IF(COUNTIF(R9:S15,"NA")>0,"NA",IF(COUNTIF(R9:S15,"PA")>0,"PA","A")))

Sheet Elias
C2: ÉVALUATION DES COMPÉTENCES EN PRATIQUE | Q2: ETML
D3: INFORMATICIEN-NE | H3: Nom et Prénom : | I3: =Consolidation!B19 -> ThomasP | N3: Nom du projet : | O3: =Consolidation!B4 -> P_BULLE
H4: Année de formation - classe : | I4: =Consolidation!B2 -> 2025-2026 / CMID2A | N4: Périodes : | O4: =Consolidation!B5 -> 40
H5: Enseignant : | I5: =Consolidation!B3 -> Xavier Carrel | N5: Dates : | O5: =Consolidation!B6 -> Du 14.1.2026 au 13.3.2026
F8: LARGEMENT ACQUIS | I8: ACQUIS | L8: PARTIELLEMENT ACQUIS | O8: NON ACQUIS | R8: Résultat
C9: COMPÉTENCES | D9: PROFESSIONNELLES | E9: Rythme de travail Rapidité, Efficacité | F9: o o o | G9: Rapide et soutenu Optimale | I9: o o o | J9: Productivité normale Respect des délais fixés | L9: o o o | M9: Lent ou irrégulier Hors délais | O9: o o o | P9: Trop lent Pas concerné par les délais
E10: Qualité du travail | F10: o o o | G10: Travail utilisable et transmissible | I10: o o o | J10: Travail utilisable et transmissible avec retouches | L10: o o o | M10: Travail nécessitant des améliorations pour être utilisable | O10: o o o | P10: Travail inutilisable
E11: Niveau de maîtrise technique | F11: o o o | G11: Maîtrise | I11: o o o | J11: Comprend et applique | L11: o o o | M11: A des lacunes, applique par mimétisme | O11: o o o | P11: Echec dans les notions de base
E12: Autonomie | F12: o o o | G12: Indépendant | I12: o o o | J12: Aide justifiée | L12: o o o | M12: Souvent besoin d'aide | O12: o o o | P12: Dépendant
D13: METHODOLOGIQUES | E13: Processus de travail | F13: o o o | G13: Intègration des règles et processus de travail | I13: o o o | J13: Respect des règles de processus de travail | L13: o o o | M13: Peu concerné | O13: o o o | P13: Pas concerné
E14: Expression orale et écrite Technique de présentation | F14: o o o | G14: Maîtrise les différents moyens et outils de communication et de documentation | I14: o o o | J14: Utilise les différents moyens et outils de communication et de documentation | L14: o o o | M14: N'utilise pas toujours les différents moyens et outils de communication et de documentation | O14: o o o | P14: Ignore la plupart des moyens et outils de communication et de documentation
E15: Approche de la durabilité et de l’innovation | F15: o o o | G15: Recours systématique aux technologies et moyens qui ménagent les ressources et les coûts | I15: o o o | J15: Utilisation régulière des technologies et moyens qui ménagent les ressources | L15: o o o | M15: Peu concerné | O15: o o o | P15: Pas concerné
D16: SOCIALES | E16: Aptitude au travail en équipe Gestion des conflits Communication | F16: o o o | G16: Influence positivement le groupe Réagit de manière réfléchie et cherche des solutions | I16: o o o | J16: Maintien les bonnes relations Ne provoque pas de conflit et participe aux solutions | L16: o o o | M16: Ne participe pas à la cohésion du groupe Réagit de manière irréfléchie et/ou disproportionnée | O16: o o o | P16: Influence négative marquée
C18: Remarque(s) : | N18: Date | P18: Signature | Q18: Totaux
L20: Enseignant : | N20: (tbd) | P20: =Consolidation!C3 -> #VALUE!
L22: Apprenti :
P24: Résultat final | Q24: =IF(COUNTBLANK(R9:S15)=14,"",IF(COUNTIF(R9:S15,"NA")>0,"NA",IF(COUNTIF(R9:S15,"PA")>0,"PA","A")))

Sheet Jonathan
C2: ÉVALUATION DES COMPÉTENCES EN PRATIQUE | Q2: ETML
D3: INFORMATICIEN-NE | H3: Nom et Prénom : | I3: =Consolidation!B10 -> Carl | N3: Nom du projet : | O3: =Consolidation!B4 -> P_BULLE
H4: Année de formation - classe : | I4: =Consolidation!B2 -> 2025-2026 / CMID2A | N4: Périodes : | O4: =Consolidation!B5 -> 40
H5: Enseignant : | I5: =Consolidation!B3 -> Xavier Carrel | N5: Dates : | O5: =Consolidation!B6 -> Du 14.1.2026 au 13.3.2026
F8: LARGEMENT ACQUIS | I8: ACQUIS | L8: PARTIELLEMENT ACQUIS | O8: NON ACQUIS | R8: Résultat
C9: COMPÉTENCES | D9: PROFESSIONNELLES | E9: Rythme de travail Rapidité, Efficacité | F9: o o o | G9: Rapide et soutenu Optimale | I9: o o o | J9: Productivité normale Respect des délais fixés | L9: o o o | M9: Lent ou irrégulier Hors délais | O9: o o o | P9: Trop lent Pas concerné par les délais
E10: Qualité du travail | F10: o o o | G10: Travail utilisable et transmissible | I10: o o o | J10: Travail utilisable et transmissible avec retouches | L10: o o o | M10: Travail nécessitant des améliorations pour être utilisable | O10: o o o | P10: Travail inutilisable
E11: Niveau de maîtrise technique | F11: o o o | G11: Maîtrise | I11: o o o | J11: Comprend et applique | L11: o o o | M11: A des lacunes, applique par mimétisme | O11: o o o | P11: Echec dans les notions de base
E12: Autonomie | F12: o o o | G12: Indépendant | I12: o o o | J12: Aide justifiée | L12: o o o | M12: Souvent besoin d'aide | O12: o o o | P12: Dépendant
D13: METHODOLOGIQUES | E13: Processus de travail | F13: o o o | G13: Intègration des règles et processus de travail | I13: o o o | J13: Respect des règles de processus de travail | L13: o o o | M13: Peu concerné | O13: o o o | P13: Pas concerné
E14: Expression orale et écrite Technique de présentation | F14: o o o | G14: Maîtrise les différents moyens et outils de communication et de documentation | I14: o o o | J14: Utilise les différents moyens et outils de communication et de documentation | L14: o o o | M14: N'utilise pas toujours les différents moyens et outils de communication et de documentation | O14: o o o | P14: Ignore la plupart des moyens et outils de communication et de documentation
E15: Approche de la durabilité et de l’innovation | F15: o o o | G15: Recours systématique aux technologies et moyens qui ménagent les ressources et les coûts | I15: o o o | J15: Utilisation régulière des technologies et moyens qui ménagent les ressources | L15: o o o | M15: Peu concerné | O15: o o o | P15: Pas concerné
D16: SOCIALES | E16: Aptitude au travail en équipe Gestion des conflits Communication | F16: o o o | G16: Influence positivement le groupe Réagit de manière réfléchie et cherche des solutions | I16: o o o | J16: Maintien les bonnes relations Ne provoque pas de conflit et participe aux solutions | L16: o o o | M16: Ne participe pas à la cohésion du groupe Réagit de manière irréfléchie et/ou disproportionnée | O16: o o o | P16: Influence négative marquée
C18: Remarque(s) : | N18: Date | P18: Signature | Q18: Totaux
L20: Enseignant : | N20: (tbd) | P20: =Consolidation!C3 -> #VALUE!
L22: Apprenti :
P24: Résultat final | Q24: =IF(COUNTBLANK(R9:S15)=14,"",IF(COUNTIF(R9:S15,"NA")>0,"NA",IF(COUNTIF(R9:S15,"PA")>0,"PA","A")))

Sheet Kilian
C2: ÉVALUATION DES COMPÉTENCES EN PRATIQUE | Q2: ETML
D3: INFORMATICIEN-NE | H3: Nom et Prénom : | I3: =Consolidation!B17 -> Ryan | N3: Nom du projet : | O3: =Consolidation!B4 -> P_BULLE
H4: Année de formation - classe : | I4: =Consolidation!B2 -> 2025-2026 / CMID2A | N4: Périodes : | O4: =Consolidation!B5 -> 40
H5: Enseignant : | I5: =Consolidation!B3 -> Xavier Carrel | N5: Dates : | O5: =Consolidation!B6 -> Du 14.1.2026 au 13.3.2026
F8: LARGEMENT ACQUIS | I8: ACQUIS | L8: PARTIELLEMENT ACQUIS | O8: NON ACQUIS | R8: Résultat
C9: COMPÉTENCES | D9: PROFESSIONNELLES | E9: Rythme de travail Rapidité, Efficacité | F9: o o o | G9: Rapide et soutenu Optimale | I9: o o o | J9: Productivité normale Respect des délais fixés | L9: o o o | M9: Lent ou irrégulier Hors délais | O9: o o o | P9: Trop lent Pas concerné par les délais
E10: Qualité du travail | F10: o o o | G10: Travail utilisable et transmissible | I10: o o o | J10: Travail utilisable et transmissible avec retouches | L10: o o o | M10: Travail nécessitant des améliorations pour être utilisable | O10: o o o | P10: Travail inutilisable
E11: Niveau de maîtrise technique | F11: o o o | G11: Maîtrise | I11: o o o | J11: Comprend et applique | L11: o o o | M11: A des lacunes, applique par mimétisme | O11: o o o | P11: Echec dans les notions de base
E12: Autonomie | F12: o o o | G12: Indépendant | I12: o o o | J12: Aide justifiée | L12: o o o | M12: Souvent besoin d'aide | O12: o o o | P12: Dépendant
D13: METHODOLOGIQUES | E13: Processus de travail | F13: o o o | G13: Intègration des règles et processus de travail | I13: o o o | J13: Respect des règles de processus de travail | L13: o o o | M13: Peu concerné | O13: o o o | P13: Pas concerné
E14: Expression orale et écrite Technique de présentation | F14: o o o | G14: Maîtrise les différents moyens et outils de communication et de documentation | I14: o o o | J14: Utilise les différents moyens et outils de communication et de documentation | L14: o o o | M14: N'utilise pas toujours les différents moyens et outils de communication et de documentation | O14: o o o | P14: Ignore la plupart des moyens et outils de communication et de documentation
E15: Approche de la durabilité et de l’innovation | F15: o o o | G15: Recours systématique aux technologies et moyens qui ménagent les ressources et les coûts | I15: o o o | J15: Utilisation régulière des technologies et moyens qui ménagent les ressources | L15: o o o | M15: Peu concerné | O15: o o o | P15: Pas concerné
D16: SOCIALES | E16: Aptitude au travail en équipe Gestion des conflits Communication | F16: o o o | G16: Influence positivement le groupe Réagit de manière réfléchie et cherche des solutions | I16: o o o | J16: Maintien les bonnes relations Ne provoque pas de conflit et participe aux solutions | L16: o o o | M16: Ne participe pas à la cohésion du groupe Réagit de manière irréfléchie et/ou disproportionnée | O16: o o o | P16: Influence négative marquée
C18: Remarque(s) : | N18: Date | P18: Signature | Q18: Totaux
L20: Enseignant : | N20: (tbd) | P20: =Consolidation!C3 -> #VALUE!
L22: Apprenti :
P24: Résultat final | Q24: =IF(COUNTBLANK(R9:S15)=14,"",IF(COUNTIF(R9:S15,"NA")>0,"NA",IF(COUNTIF(R9:S15,"PA")>0,"PA","A")))

Sheet Latif
C2: ÉVALUATION DES COMPÉTENCES EN PRATIQUE | Q2: ETML
D3: INFORMATICIEN-NE | H3: Nom et Prénom : | I3: =Consolidation!B11 -> David | N3: Nom du projet : | O3: =Consolidation!B4 -> P_BULLE
H4: Année de formation - classe : | I4: =Consolidation!B2 -> 2025-2026 / CMID2A | N4: Périodes : | O4: =Consolidation!B5 -> 40
H5: Enseignant : | I5: =Consolidation!B3 -> Xavier Carrel | N5: Dates : | O5: =Consolidation!B6 -> Du 14.1.2026 au 13.3.2026
F8: LARGEMENT ACQUIS | I8: ACQUIS | L8: PARTIELLEMENT ACQUIS | O8: NON ACQUIS | R8: Résultat
C9: COMPÉTENCES | D9: PROFESSIONNELLES | E9: Rythme de travail Rapidité, Efficacité | F9: o o o | G9: Rapide et soutenu Optimale | I9: o o o | J9: Productivité normale Respect des délais fixés | L9: o o o | M9: Lent ou irrégulier Hors délais | O9: o o o | P9: Trop lent Pas concerné par les délais
E10: Qualité du travail | F10: o o o | G10: Travail utilisable et transmissible | I10: o o o | J10: Travail utilisable et transmissible avec retouches | L10: o o o | M10: Travail nécessitant des améliorations pour être utilisable | O10: o o o | P10: Travail inutilisable
E11: Niveau de maîtrise technique | F11: o o o | G11: Maîtrise | I11: o o o | J11: Comprend et applique | L11: o o o | M11: A des lacunes, applique par mimétisme | O11: o o o | P11: Echec dans les notions de base
E12: Autonomie | F12: o o o | G12: Indépendant | I12: o o o | J12: Aide justifiée | L12: o o o | M12: Souvent besoin d'aide | O12: o o o | P12: Dépendant
D13: METHODOLOGIQUES | E13: Processus de travail | F13: o o o | G13: Intègration des règles et processus de travail | I13: o o o | J13: Respect des règles de processus de travail | L13: o o o | M13: Peu concerné | O13: o o o | P13: Pas concerné
E14: Expression orale et écrite Technique de présentation | F14: o o o | G14: Maîtrise les différents moyens et outils de communication et de documentation | I14: o o o | J14: Utilise les différents moyens et outils de communication et de documentation | L14: o o o | M14: N'utilise pas toujours les différents moyens et outils de communication et de documentation | O14: o o o | P14: Ignore la plupart des moyens et outils de communication et de documentation
E15: Approche de la durabilité et de l’innovation | F15: o o o | G15: Recours systématique aux technologies et moyens qui ménagent les ressources et les coûts | I15: o o o | J15: Utilisation régulière des technologies et moyens qui ménagent les ressources | L15: o o o | M15: Peu concerné | O15: o o o | P15: Pas concerné
D16: SOCIALES | E16: Aptitude au travail en équipe Gestion des conflits Communication | F16: o o o | G16: Influence positivement le groupe Réagit de manière réfléchie et cherche des solutions | I16: o o o | J16: Maintien les bonnes relations Ne provoque pas de conflit et participe aux solutions | L16: o o o | M16: Ne participe pas à la cohésion du groupe Réagit de manière irréfléchie et/ou disproportionnée | O16: o o o | P16: Influence négative marquée
C18: Remarque(s) : | N18: Date | P18: Signature | Q18: Totaux
L20: Enseignant : | N20: (tbd) | P20: =Consolidation!C3 -> #VALUE!
L22: Apprenti :
P24: Résultat final | Q24: =IF(COUNTBLANK(R9:S15)=14,"",IF(COUNTIF(R9:S15,"NA")>0,"NA",IF(COUNTIF(R9:S15,"PA")>0,"PA","A")))

Sheet Néo
C2: ÉVALUATION DES COMPÉTENCES EN PRATIQUE | Q2: ETML
D3: INFORMATICIEN-NE | H3: Nom et Prénom : | I3: =Consolidation!B9 -> Camille | N3: Nom du projet : | O3: =Consolidation!B4 -> P_BULLE
H4: Année de formation - classe : | I4: =Consolidation!B2 -> 2025-2026 / CMID2A | N4: Périodes : | O4: =Consolidation!B5 -> 40
H5: Enseignant : | I5: =Consolidation!B3 -> Xavier Carrel | N5: Dates : | O5: =Consolidation!B6 -> Du 14.1.2026 au 13.3.2026
F8: LARGEMENT ACQUIS | I8: ACQUIS | L8: PARTIELLEMENT ACQUIS | O8: NON ACQUIS | R8: Résultat
C9: COMPÉTENCES | D9: PROFESSIONNELLES | E9: Rythme de travail Rapidité, Efficacité | F9: o o o | G9: Rapide et soutenu Optimale | I9: o o o | J9: Productivité normale Respect des délais fixés | L9: o o o | M9: Lent ou irrégulier Hors délais | O9: o o o | P9: Trop lent Pas concerné par les délais
E10: Qualité du travail | F10: o o o | G10: Travail utilisable et transmissible | I10: o o o | J10: Travail utilisable et transmissible avec retouches | L10: o o o | M10: Travail nécessitant des améliorations pour être utilisable | O10: o o o | P10: Travail inutilisable
E11: Niveau de maîtrise technique | F11: o o o | G11: Maîtrise | I11: o o o | J11: Comprend et applique | L11: o o o | M11: A des lacunes, applique par mimétisme | O11: o o o | P11: Echec dans les notions de base
E12: Autonomie | F12: o o o | G12: Indépendant | I12: o o o | J12: Aide justifiée | L12: o o o | M12: Souvent besoin d'aide | O12: o o o | P12: Dépendant
D13: METHODOLOGIQUES | E13: Processus de travail | F13: o o o | G13: Intègration des règles et processus de travail | I13: o o o | J13: Respect des règles de processus de travail | L13: o o o | M13: Peu concerné | O13: o o o | P13: Pas concerné
E14: Expression orale et écrite Technique de présentation | F14: o o o | G14: Maîtrise les différents moyens et outils de communication et de documentation | I14: o o o | J14: Utilise les différents moyens et outils de communication et de documentation | L14: o o o | M14: N'utilise pas toujours les différents moyens et outils de communication et de documentation | O14: o o o | P14: Ignore la plupart des moyens et outils de communication et de documentation
E15: Approche de la durabilité et de l’innovation | F15: o o o | G15: Recours systématique aux technologies et moyens qui ménagent les ressources et les coûts | I15: o o o | J15: Utilisation régulière des technologies et moyens qui ménagent les ressources | L15: o o o | M15: Peu concerné | O15: o o o | P15: Pas concerné
D16: SOCIALES | E16: Aptitude au travail en équipe Gestion des conflits Communication | F16: o o o | G16: Influence positivement le groupe Réagit de manière réfléchie et cherche des solutions | I16: o o o | J16: Maintien les bonnes relations Ne provoque pas de conflit et participe aux solutions | L16: o o o | M16: Ne participe pas à la cohésion du groupe Réagit de manière irréfléchie et/ou disproportionnée | O16: o o o | P16: Influence négative marquée
C18: Remarque(s) : | N18: Date | P18: Signature | Q18: Totaux
L20: Enseignant : | N20: (tbd) | P20: =Consolidation!C3 -> #VALUE!
L22: Apprenti :
P24: Résultat final | Q24: =IF(COUNTBLANK(R9:S15)=14,"",IF(COUNTIF(R9:S15,"NA")>0,"NA",IF(COUNTIF(R9:S15,"PA")>0,"PA","A")))

Sheet Ryan
C2: ÉVALUATION DES COMPÉTENCES EN PRATIQUE | Q2: ETML
D3: INFORMATICIEN-NE | H3: Nom et Prénom : | I3: =Consolidation!B12 -> Elias | N3: Nom du projet : | O3: =Consolidation!B4 -> P_BULLE
H4: Année de formation - classe : | I4: =Consolidation!B2 -> 2025-2026 / CMID2A | N4: Périodes : | O4: =Consolidation!B5 -> 40
H5: Enseignant : | I5: =Consolidation!B3 -> Xavier Carrel | N5: Dates : | O5: =Consolidation!B6 -> Du 14.1.2026 au 13.3.2026
F8: LARGEMENT ACQUIS | I8: ACQUIS | L8: PARTIELLEMENT ACQUIS | O8: NON ACQUIS | R8: Résultat
C9: COMPÉTENCES | D9: PROFESSIONNELLES | E9: Rythme de travail Rapidité, Efficacité | F9: o o o | G9: Rapide et soutenu Optimale | I9: o o o | J9: Productivité normale Respect des délais fixés | L9: o o o | M9: Lent ou irrégulier Hors délais | O9: o o o | P9: Trop lent Pas concerné par les délais
E10: Qualité du travail | F10: o o o | G10: Travail utilisable et transmissible | I10: o o o | J10: Travail utilisable et transmissible avec retouches | L10: o o o | M10: Travail nécessitant des améliorations pour être utilisable | O10: o o o | P10: Travail inutilisable
E11: Niveau de maîtrise technique | F11: o o o | G11: Maîtrise | I11: o o o | J11: Comprend et applique | L11: o o o | M11: A des lacunes, applique par mimétisme | O11: o o o | P11: Echec dans les notions de base
E12: Autonomie | F12: o o o | G12: Indépendant | I12: o o o | J12: Aide justifiée | L12: o o o | M12: Souvent besoin d'aide | O12: o o o | P12: Dépendant
D13: METHODOLOGIQUES | E13: Processus de travail | F13: o o o | G13: Intègration des règles et processus de travail | I13: o o o | J13: Respect des règles de processus de travail | L13: o o o | M13: Peu concerné | O13: o o o | P13: Pas concerné
E14: Expression orale et écrite Technique de présentation | F14: o o o | G14: Maîtrise les différents moyens et outils de communication et de documentation | I14: o o o | J14: Utilise les différents moyens et outils de communication et de documentation | L14: o o o | M14: N'utilise pas toujours les différents moyens et outils de communication et de documentation | O14: o o o | P14: Ignore la plupart des moyens et outils de communication et de documentation
E15: Approche de la durabilité et de l’innovation | F15: o o o | G15: Recours systématique aux technologies et moyens qui ménagent les ressources et les coûts | I15: o o o | J15: Utilisation régulière des technologies et moyens qui ménagent les ressources | L15: o o o | M15: Peu concerné | O15: o o o | P15: Pas concerné
D16: SOCIALES | E16: Aptitude au travail en équipe Gestion des conflits Communication | F16: o o o | G16: Influence positivement le groupe Réagit de manière réfléchie et cherche des solutions | I16: o o o | J16: Maintien les bonnes relations Ne provoque pas de conflit et participe aux solutions | L16: o o o | M16: Ne participe pas à la cohésion du groupe Réagit de manière irréfléchie et/ou disproportionnée | O16: o o o | P16: Influence négative marquée
C18: Remarque(s) : | N18: Date | P18: Signature | Q18: Totaux
L20: Enseignant : | N20: (tbd) | P20: =Consolidation!C3 -> #VALUE!
L22: Apprenti :
P24: Résultat final | Q24: =IF(COUNTBLANK(R9:S15)=14,"",IF(COUNTIF(R9:S15,"NA")>0,"NA",IF(COUNTIF(R9:S15,"PA")>0,"PA","A")))

Sheet Stepan
C2: ÉVALUATION DES COMPÉTENCES EN PRATIQUE | Q2: ETML
D3: INFORMATICIEN-NE | H3: Nom et Prénom : | I3: =Consolidation!B13 -> Jonathan | N3: Nom du projet : | O3: =Consolidation!B4 -> P_BULLE
H4: Année de formation - classe : | I4: =Consolidation!B2 -> 2025-2026 / CMID2A | N4: Périodes : | O4: =Consolidation!B5 -> 40
H5: Enseignant : | I5: =Consolidation!B3 -> Xavier Carrel | N5: Dates : | O5: =Consolidation!B6 -> Du 14.1.2026 au 13.3.2026
F8: LARGEMENT ACQUIS | I8: ACQUIS | L8: PARTIELLEMENT ACQUIS | O8: NON ACQUIS | R8: Résultat
C9: COMPÉTENCES | D9: PROFESSIONNELLES | E9: Rythme de travail Rapidité, Efficacité | F9: o o o | G9: Rapide et soutenu Optimale | I9: o o o | J9: Productivité normale Respect des délais fixés | L9: o o o | M9: Lent ou irrégulier Hors délais | O9: o o o | P9: Trop lent Pas concerné par les délais
E10: Qualité du travail | F10: o o o | G10: Travail utilisable et transmissible | I10: o o o | J10: Travail utilisable et transmissible avec retouches | L10: o o o | M10: Travail nécessitant des améliorations pour être utilisable | O10: o o o | P10: Travail inutilisable
E11: Niveau de maîtrise technique | F11: o o o | G11: Maîtrise | I11: o o o | J11: Comprend et applique | L11: o o o | M11: A des lacunes, applique par mimétisme | O11: o o o | P11: Echec dans les notions de base | AB11: F
E12: Autonomie | F12: o o o | G12: Indépendant | I12: o o o | J12: Aide justifiée | L12: o o o | M12: Souvent besoin d'aide | O12: o o o | P12: Dépendant
D13: METHODOLOGIQUES | E13: Processus de travail | F13: o o o | G13: Intègration des règles et processus de travail | I13: o o o | J13: Respect des règles de processus de travail | L13: o o o | M13: Peu concerné | O13: o o o | P13: Pas concerné
E14: Expression orale et écrite Technique de présentation | F14: o o o | G14: Maîtrise les différents moyens et outils de communication et de documentation | I14: o o o | J14: Utilise les différents moyens et outils de communication et de documentation | L14: o o o | M14: N'utilise pas toujours les différents moyens et outils de communication et de documentation | O14: o o o | P14: Ignore la plupart des moyens et outils de communication et de documentation
E15: Approche de la durabilité et de l’innovation | F15: o o o | G15: Recours systématique aux technologies et moyens qui ménagent les ressources et les coûts | I15: o o o | J15: Utilisation régulière des technologies et moyens qui ménagent les ressources | L15: o o o | M15: Peu concerné | O15: o o o | P15: Pas concerné
D16: SOCIALES | E16: Aptitude au travail en équipe Gestion des conflits Communication | F16: o o o | G16: Influence positivement le groupe Réagit de manière réfléchie et cherche des solutions | I16: o o o | J16: Maintien les bonnes relations Ne provoque pas de conflit et participe aux solutions | L16: o o o | M16: Ne participe pas à la cohésion du groupe Réagit de manière irréfléchie et/ou disproportionnée | O16: o o o | P16: Influence négative marquée
C18: Remarque(s) : | N18: Date | P18: Signature | Q18: Totaux
L20: Enseignant : | N20: (tbd) | P20: =Consolidation!C3 -> #VALUE!
L22: Apprenti :
P24: Résultat final | Q24: =IF(COUNTBLANK(R9:S15)=14,"",IF(COUNTIF(R9:S15,"NA")>0,"NA",IF(COUNTIF(R9:S15,"PA")>0,"PA","A")))

Sheet ThomasP
C2: ÉVALUATION DES COMPÉTENCES EN PRATIQUE | Q2: ETML
D3: INFORMATICIEN-NE | H3: Nom et Prénom : | I3: =Consolidation!B14 -> Kilian | N3: Nom du projet : | O3: =Consolidation!B4 -> P_BULLE
H4: Année de formation - classe : | I4: =Consolidation!B2 -> 2025-2026 / CMID2A | N4: Périodes : | O4: =Consolidation!B5 -> 40
H5: Enseignant : | I5: =Consolidation!B3 -> Xavier Carrel | N5: Dates : | O5: =Consolidation!B6 -> Du 14.1.2026 au 13.3.2026
F8: LARGEMENT ACQUIS | I8: ACQUIS | L8: PARTIELLEMENT ACQUIS | O8: NON ACQUIS | R8: Résultat
C9: COMPÉTENCES | D9: PROFESSIONNELLES | E9: Rythme de travail Rapidité, Efficacité | F9: o o o | G9: Rapide et soutenu Optimale | I9: o o o | J9: Productivité normale Respect des délais fixés | L9: o o o | M9: Lent ou irrégulier Hors délais | O9: o o o | P9: Trop lent Pas concerné par les délais
E10: Qualité du travail | F10: o o o | G10: Travail utilisable et transmissible | I10: o o o | J10: Travail utilisable et transmissible avec retouches | L10: o o o | M10: Travail nécessitant des améliorations pour être utilisable | O10: o o o | P10: Travail inutilisable
E11: Niveau de maîtrise technique | F11: o o o | G11: Maîtrise | I11: o o o | J11: Comprend et applique | L11: o o o | M11: A des lacunes, applique par mimétisme | O11: o o o | P11: Echec dans les notions de base
E12: Autonomie | F12: o o o | G12: Indépendant | I12: o o o | J12: Aide justifiée | L12: o o o | M12: Souvent besoin d'aide | O12: o o o | P12: Dépendant
D13: METHODOLOGIQUES | E13: Processus de travail | F13: o o o | G13: Intègration des règles et processus de travail | I13: o o o | J13: Respect des règles de processus de travail | L13: o o o | M13: Peu concerné | O13: o o o | P13: Pas concerné
E14: Expression orale et écrite Technique de présentation | F14: o o o | G14: Maîtrise les différents moyens et outils de communication et de documentation | I14: o o o | J14: Utilise les différents moyens et outils de communication et de documentation | L14: o o o | M14: N'utilise pas toujours les différents moyens et outils de communication et de documentation | O14: o o o | P14: Ignore la plupart des moyens et outils de communication et de documentation
E15: Approche de la durabilité et de l’innovation | F15: o o o | G15: Recours systématique aux technologies et moyens qui ménagent les ressources et les coûts | I15: o o o | J15: Utilisation régulière des technologies et moyens qui ménagent les ressources | L15: o o o | M15: Peu concerné | O15: o o o | P15: Pas concerné
D16: SOCIALES | E16: Aptitude au travail en équipe Gestion des conflits Communication | F16: o o o | G16: Influence positivement le groupe Réagit de manière réfléchie et cherche des solutions | I16: o o o | J16: Maintien les bonnes relations Ne provoque pas de conflit et participe aux solutions | L16: o o o | M16: Ne participe pas à la cohésion du groupe Réagit de manière irréfléchie et/ou disproportionnée | O16: o o o | P16: Influence négative marquée
C18: Remarque(s) : | N18: Date | P18: Signature | Q18: Totaux
L20: Enseignant : | N20: (tbd) | P20: =Consolidation!C3 -> #VALUE!
L22: Apprenti :
P24: Résultat final | Q24: =IF(COUNTBLANK(R9:S15)=14,"",IF(COUNTIF(R9:S15,"NA")>0,"NA",IF(COUNTIF(R9:S15,"PA")>0,"PA","A")))

Sheet ThomasR
C2: ÉVALUATION DES COMPÉTENCES EN PRATIQUE | Q2: ETML
D3: INFORMATICIEN-NE | H3: Nom et Prénom : | I3: =Consolidation!B15 -> Latif | N3: Nom du projet : | O3: =Consolidation!B4 -> P_BULLE
H4: Année de formation - classe : | I4: =Consolidation!B2 -> 2025-2026 / CMID2A | N4: Périodes : | O4: =Consolidation!B5 -> 40
H5: Enseignant : | I5: =Consolidation!B3 -> Xavier Carrel | N5: Dates : | O5: =Consolidation!B6 -> Du 14.1.2026 au 13.3.2026
F8: LARGEMENT ACQUIS | I8: ACQUIS | L8: PARTIELLEMENT ACQUIS | O8: NON ACQUIS | R8: Résultat
C9: COMPÉTENCES | D9: PROFESSIONNELLES | E9: Rythme de travail Rapidité, Efficacité | F9: o o o | G9: Rapide et soutenu Optimale | I9: o o o | J9: Productivité normale Respect des délais fixés | L9: o o o | M9: Lent ou irrégulier Hors délais | O9: o o o | P9: Trop lent Pas concerné par les délais
E10: Qualité du travail | F10: o o o | G10: Travail utilisable et transmissible | I10: o o o | J10: Travail utilisable et transmissible avec retouches | L10: o o o | M10: Travail nécessitant des améliorations pour être utilisable | O10: o o o | P10: Travail inutilisable
E11: Niveau de maîtrise technique | F11: o o o | G11: Maîtrise | I11: o o o | J11: Comprend et applique | L11: o o o | M11: A des lacunes, applique par mimétisme | O11: o o o | P11: Echec dans les notions de base | AB11: H
E12: Autonomie | F12: o o o | G12: Indépendant | I12: o o o | J12: Aide justifiée | L12: o o o | M12: Souvent besoin d'aide | O12: o o o | P12: Dépendant
D13: METHODOLOGIQUES | E13: Processus de travail | F13: o o o | G13: Intègration des règles et processus de travail | I13: o o o | J13: Respect des règles de processus de travail | L13: o o o | M13: Peu concerné | O13: o o o | P13: Pas concerné
E14: Expression orale et écrite Technique de présentation | F14: o o o | G14: Maîtrise les différents moyens et outils de communication et de documentation | I14: o o o | J14: Utilise les différents moyens et outils de communication et de documentation | L14: o o o | M14: N'utilise pas toujours les différents moyens et outils de communication et de documentation | O14: o o o | P14: Ignore la plupart des moyens et outils de communication et de documentation
E15: Approche de la durabilité et de l’innovation | F15: o o o | G15: Recours systématique aux technologies et moyens qui ménagent les ressources et les coûts | I15: o o o | J15: Utilisation régulière des technologies et moyens qui ménagent les ressources | L15: o o o | M15: Peu concerné | O15: o o o | P15: Pas concerné
D16: SOCIALES | E16: Aptitude au travail en équipe Gestion des conflits Communication | F16: o o o | G16: Influence positivement le groupe Réagit de manière réfléchie et cherche des solutions | I16: o o o | J16: Maintien les bonnes relations Ne provoque pas de conflit et participe aux solutions | L16: o o o | M16: Ne participe pas à la cohésion du groupe Réagit de manière irréfléchie et/ou disproportionnée | O16: o o o | P16: Influence négative marquée
C18: Remarque(s) : | N18: Date | P18: Signature | Q18: Totaux
L20: Enseignant : | N20: (tbd) | P20: =Consolidation!C3 -> #VALUE!
L22: Apprenti :
P24: Résultat final | Q24: =IF(COUNTBLANK(R9:S15)=14,"",IF(COUNTIF(R9:S15,"NA")>0,"NA",IF(COUNTIF(R9:S15,"PA")>0,"PA","A")))
